{
  "schemaVersion": 1,
  "generatedAt": "2026-06-21T13:08:29.136Z",
  "sourceSets": "data/scryfall-sets.json",
  "selector": "reviewed",
  "setCount": 3,
  "sets": [
    {
      "code": "lea",
      "name": "Limited Edition Alpha",
      "releasedAt": "1993-08-05",
      "setType": "core",
      "cardCount": 295,
      "digital": false,
      "printCount": 295,
      "uniqueNameCount": 290,
      "filePath": "data/card-name-lists/lea-card-names.txt"
    },
    {
      "code": "leb",
      "name": "Limited Edition Beta",
      "releasedAt": "1993-10-04",
      "setType": "core",
      "cardCount": 302,
      "digital": false,
      "printCount": 302,
      "uniqueNameCount": 292,
      "filePath": "data/card-name-lists/leb-card-names.txt"
    },
    {
      "code": "arn",
      "name": "Arabian Nights",
      "releasedAt": "1993-12-17",
      "setType": "expansion",
      "cardCount": 92,
      "digital": false,
      "printCount": 78,
      "uniqueNameCount": 78,
      "filePath": "data/card-name-lists/arn-card-names.txt"
    }
  ]
}
